{
  "id": "h_1724a190b00007",
  "hinban": "A-190",
  "title": "【超ド級の背徳感】 稼ぐ旦那さんに放置されて、暇を持て余した美人若妻が興味本位からAV出演！経験少ない初々しい感じ方に興奮して、思わず中出し！",
  "review": "<h3>禁断の『主婦』が抱く『不倫』の魔法――旦那留守中、寝取られへの衝動が止まらない！</h3>\n\n<p>まず、まるで映画の中に引き込まれた瞬間のような感覚―それがこの作品で描かれる、穏やかでありながらも煽りたぎる主婦の心。稼ぐ旦那を余韻で残し、孤独に閉ざされた部屋で揺れる欲望の波。彼女の裏切り心とともに、朝まで残る寂しさと胸の高鳴り。舞台はシンプルだが、情感の鋭さはまさに不倫の神髄を偶像化している。</p>\n\n<p>旦那の留守中――それはただの一時的な暇つぶしではない。彼女にとっては親密さの欠如を埋めるための荒野。そこで芽生えた好奇心は、伸びるときにしか触れられない「背徳の泥沼」へと彼女を引きゆっくりと誘う。視覚的にはシンプルな家の中だが、心理の迷宮はまるで雨が止まるまでの静止した血潮を呼び覚ます――その満たされぬ欲求が、カメラの光とともに彼女を包み込む。</p>\n\n<p>「新鮮なエクスペリエンス、初々しい刺激――それが彼女を突き動かしたのだ。」涙が流れたり、颯爽とした笑顔が出てきたりする瞬間は、瞬間ごとに息散らし、閉じ込めた欲望を解き放つ。未経験者ならではのドキダキ感が、聖なる瞬間となり、彼女はかつてなかった自分を見つける時なんだ。</p>\n\n<p>克明な描写を避けつつも、まるで空気が煽られたように、熱爆発が導くエクストリームな感覚が語られる。見る者は、キスよりもさらに激しく、言葉で語り尽くせぬ心の奥底を踏みしめるだろう。寝取られの緊張感と、ほのかな甘い逃避感が交差するその場面は、まさに成人の心を揺り動かす饗宴。</p>\n\n<p>結末は、覚悟の上に築かれた愛への戸締まり。まるで透過する光のように、彼女の内輪に刻まれた欲望は、装飾的なる主路で簡潔に抉れくる。観の胸に届くのは、潜在的な情動への執着と、秘密の鍵を握る愛の結果々だ。</p>\n\n<p>こちらの作品は、堅苦しい日常生活と極限の情熱が打ち合う場面が、繊細でありながら暗い情緒で満ち溢れています。みなさん、もしこの世界に足を踏み入れたくなったなら、躊躇せずに『主婦』の奥行き、そして『不倫』の激しさを体験してみてください。絶対に忘れられない背徳の一夜が待っています。</p>",
  "image": "https://pics.dmm.co.jp/digital/video/h_1724a190b00007/h_1724a190b00007pl.jpg",
  "sample_images": [
    "https://pics.dmm.co.jp/digital/video/h_1724a190b00007/h_1724a190b00007jp-1.jpg",
    "https://pics.dmm.co.jp/digital/video/h_1724a190b00007/h_1724a190b00007jp-2.jpg",
    "https://pics.dmm.co.jp/digital/video/h_1724a190b00007/h_1724a190b00007jp-3.jpg",
    "https://pics.dmm.co.jp/digital/video/h_1724a190b00007/h_1724a190b00007jp-4.jpg",
    "https://pics.dmm.co.jp/digital/video/h_1724a190b00007/h_1724a190b00007jp-5.jpg",
    "https://pics.dmm.co.jp/digital/video/h_1724a190b00007/h_1724a190b00007jp-6.jpg",
    "https://pics.dmm.co.jp/digital/video/h_1724a190b00007/h_1724a190b00007jp-7.jpg",
    "https://pics.dmm.co.jp/digital/video/h_1724a190b00007/h_1724a190b00007jp-8.jpg",
    "https://pics.dmm.co.jp/digital/video/h_1724a190b00007/h_1724a190b00007jp-9.jpg",
    "https://pics.dmm.co.jp/digital/video/h_1724a190b00007/h_1724a190b00007jp-10.jpg",
    "https://pics.dmm.co.jp/digital/video/h_1724a190b00007/h_1724a190b00007jp-11.jpg",
    "https://pics.dmm.co.jp/digital/video/h_1724a190b00007/h_1724a190b00007jp-12.jpg",
    "https://pics.dmm.co.jp/digital/video/h_1724a190b00007/h_1724a190b00007jp-13.jpg",
    "https://pics.dmm.co.jp/digital/video/h_1724a190b00007/h_1724a190b00007jp-14.jpg",
    "https://pics.dmm.co.jp/digital/video/h_1724a190b00007/h_1724a190b00007jp-15.jpg"
  ],
  "affiliate_url": "https://al.fanza.co.jp/?lurl=https%3A%2F%2Fvideo.dmm.co.jp%2Fav%2Fcontent%2F%3Fid%3Dh_1724a190b00007&af_id=onchan555-003&ch=api",
  "genres": [
    "ハイビジョン",
    "中出し",
    "アクメ・オーガズム",
    "クンニ",
    "フェラ",
    "パイパン",
    "尻フェチ",
    "貧乳・微乳",
    "ナンパ",
    "素人",
    "人妻・主婦"
  ],
  "actresses": [],
  "maker": "即ヌキ",
  "date": "2026-07-14 00:00:00",
  "labels": [
    "FANZA新作",
    "人妻",
    "ネトラレ",
    "背徳不倫"
  ]
}