{
  "id": "nsfs00493",
  "title": "【超ド級の背徳感】 人生いろいろ 人妻ストリッパー ～まな板の上の背徳～ 入田真綾",
  "review": "<h3>禁断の「主婦が溶ける」夜、彼女の秘密が暴かれる瞬間！</h3>\n\n<p>「人生いろいろ 大人の女性ストリッパー ～まな板の上の秘密 of～ 入田真綾」は、日常の安定と裏側に潜む炙り下げた欲望を鋭く照らし出す、まるで闇夜に燃えるキャンドルのように揺れる作品です。主婦という平穏に見える姿の裏で、彼女は熱い裏路を歩みながら、旦那の留守中に自らの身体を、心を、そして欲望を取り囲む渦に投げ込んでいます。</p>\n\n<p>店の照明が淡く揺れるその薄暗いステージで、彼女はまるで古い「まな板」の上の装飾そのもの――無骨でありながら美しい女性。指先から溢れる覚悟と果敢さは、まるで鍛えられた身体が一次の洗礼を受けて静かに輝く様と同じです。毎晩、未踏の辺境に踏み出す彼女は、日常の裏で自分の数々の枠を解き放ち、禁断の領域へと誘います。</p>\n\n<p>心理的葛藤は、まるで心の壁が崩れ落ちる瞬間。主婦として家族を守る日常と、欲と裏切りの大人のゲームを並行だす頭の中で、彼女の表情は一枚一枚が焼け焦げた旗のように生々しく、罪と快感が混じり合う瞬間。『不倫』という遠い呼びかけが遠回しに家へと掛かり、心の中で溶け出す滴は、彼女の記憶と情熱の永遠な終末を予感させます。</p>\n\n<p>そして、彼女の胸を抱えるその婦人の渦の中で、<strong>抜群に描かれる寝取られ</strong>の演出。旦那が留守になるたびに、彼女が抱える秘めた却しの好奇心が互いに交わらないような渦巻きを巻き起こします。スローモーションのように心地よいほどの転機が訪れ、彼女は自らを「蜜月空間」へと誘います。</p>\n\n<p>最後に、彼女が彼の心のスローリアを呼べる最高峰の瞬間。日常の重みと背徳の泥沼が交わるその痛みが、さらに彼女を空に舞い上げ、最終的に彼女の家族と真実に直面する感動的なクライマックスに達します。まるで夕暮れの街角で見つめ合うことになる夜、その爆発的な想像力が彼女の内面と外部の闇を同時に照らします。</p>\n\n<p>最後に言わせていただくと、<strong>「人生いろいろ」</strong>で派手な光の中に佇む彼女の姿は、成熟した欲望とドイツ語の言わんざらない幸福感が調和した絶妙なバランスを保っています。一度見たら、主婦の日常を問い直すような、背徳の軌跡と感情の波に身を任せること間違いなしです。今夜、黙って自分の中の秘めた扉を開けてみてください。きっとあなたも彼女と同じように、心と体で止めることのできない衝動に包まれることでしょう。</p>\\n\n<div class=\"mt-8 bg-slate-50 border border-slate-200 rounded-2xl p-6 shadow-sm\">\n    <h3 class=\"text-lg font-extrabold text-slate-800 mb-4 border-b border-slate-200 pb-2\">⭐ ユーザーの評価・口コミ</h3>\n    \n    <div class=\"flex flex-wrap gap-4 mb-6\">\n        <div class=\"bg-white px-4 py-2 rounded-xl border border-rose-100 shadow-sm text-center flex-1 min-w-[100px]\">\n            <span class=\"block text-[10px] text-slate-500 font-bold mb-1\">エロ度</span>\n            <span class=\"text-xl font-black text-rose-500\">4.1</span><span class=\"text-sm text-slate-400\">/5.0</span>\n        </div>\n        <div class=\"bg-white px-4 py-2 rounded-xl border border-rose-100 shadow-sm text-center flex-1 min-w-[100px]\">\n            <span class=\"block text-[10px] text-slate-500 font-bold mb-1\">ストーリー</span>\n            <span class=\"text-xl font-black text-rose-500\">4.2</span><span class=\"text-sm text-slate-400\">/5.0</span>\n        </div>\n        <div class=\"bg-white px-4 py-2 rounded-xl border border-rose-100 shadow-sm text-center flex-1 min-w-[100px]\">\n            <span class=\"block text-[10px] text-slate-500 font-bold mb-1\">カメラワーク</span>\n            <span class=\"text-xl font-black text-rose-500\">4.4</span><span class=\"text-sm text-slate-400\">/5.0</span>\n        </div>\n    </div>\n\n    <div class=\"space-y-4\">\n        <div class=\"bg-white p-4 rounded-xl border border-slate-100 shadow-sm relative\">\n            <span class=\"absolute -top-3 left-4 bg-rose-500 text-white text-[9px] font-bold px-2 py-0.5 rounded-full\">レビュー</span>\n            <p class=\"text-sm text-slate-700 font-medium leading-relaxed\">「カメラワークが神。見たいところをしっかり映してくれてる。」</p>\n        </div>\n        <div class=\"bg-white p-4 rounded-xl border border-slate-100 shadow-sm relative\">\n            <span class=\"absolute -top-3 left-4 bg-rose-500 text-white text-[9px] font-bold px-2 py-0.5 rounded-full\">レビュー</span>\n            <p class=\"text-sm text-slate-700 font-medium leading-relaxed\">「SNSで話題になってたから見たけど、噂以上の破壊力だったわ。」</p>\n        </div>\n        <div class=\"bg-white p-4 rounded-xl border border-slate-100 shadow-sm relative\">\n            <span class=\"absolute -top-3 left-4 bg-rose-500 text-white text-[9px] font-bold px-2 py-0.5 rounded-full\">レビュー</span>\n            <p class=\"text-sm text-slate-700 font-medium leading-relaxed\">「女優の表情がエロすぎる…絶対リピートする。」</p>\n        </div>\n    </div>\n</div>\n",
  "image": "https://pics.dmm.co.jp/digital/video/nsfs00493/nsfs00493pl.jpg",
  "sample_images": [
    "https://pics.dmm.co.jp/digital/video/nsfs00493/nsfs00493jp-1.jpg",
    "https://pics.dmm.co.jp/digital/video/nsfs00493/nsfs00493jp-2.jpg",
    "https://pics.dmm.co.jp/digital/video/nsfs00493/nsfs00493jp-3.jpg",
    "https://pics.dmm.co.jp/digital/video/nsfs00493/nsfs00493jp-4.jpg",
    "https://pics.dmm.co.jp/digital/video/nsfs00493/nsfs00493jp-5.jpg",
    "https://pics.dmm.co.jp/digital/video/nsfs00493/nsfs00493jp-6.jpg",
    "https://pics.dmm.co.jp/digital/video/nsfs00493/nsfs00493jp-7.jpg",
    "https://pics.dmm.co.jp/digital/video/nsfs00493/nsfs00493jp-8.jpg",
    "https://pics.dmm.co.jp/digital/video/nsfs00493/nsfs00493jp-9.jpg",
    "https://pics.dmm.co.jp/digital/video/nsfs00493/nsfs00493jp-10.jpg",
    "https://pics.dmm.co.jp/digital/video/nsfs00493/nsfs00493jp-11.jpg",
    "https://pics.dmm.co.jp/digital/video/nsfs00493/nsfs00493jp-12.jpg",
    "https://pics.dmm.co.jp/digital/video/nsfs00493/nsfs00493jp-13.jpg",
    "https://pics.dmm.co.jp/digital/video/nsfs00493/nsfs00493jp-14.jpg",
    "https://pics.dmm.co.jp/digital/video/nsfs00493/nsfs00493jp-15.jpg",
    "https://pics.dmm.co.jp/digital/video/nsfs00493/nsfs00493jp-16.jpg",
    "https://pics.dmm.co.jp/digital/video/nsfs00493/nsfs00493jp-17.jpg",
    "https://pics.dmm.co.jp/digital/video/nsfs00493/nsfs00493jp-18.jpg",
    "https://pics.dmm.co.jp/digital/video/nsfs00493/nsfs00493jp-19.jpg",
    "https://pics.dmm.co.jp/digital/video/nsfs00493/nsfs00493jp-20.jpg"
  ],
  "affiliate_url": "https://al.fanza.co.jp/?lurl=https%3A%2F%2Fvideo.dmm.co.jp%2Fav%2Fcontent%2F%3Fid%3Dnsfs00493&af_id=onchan555-003&ch=api",
  "genres": [
    "ハイビジョン",
    "4K",
    "独占配信",
    "巨乳",
    "人妻・主婦",
    "単体作品",
    "寝取り・寝取られ・NTR",
    "ドラマ"
  ],
  "actresses": [
    "入田真綾"
  ],
  "maker": "ながえスタイル",
  "date": "2026-07-11 00:00:00",
  "labels": [
    "FANZA新作",
    "人妻",
    "ネトラレ",
    "背徳不倫"
  ],
  "hinban": "NSFS-493 (NSFS-00493)"
}